{
  "users": [
    {
      "id": 1,
      "name": "Java",
      "certified": "Great Learning",
      "color": "red",
      "logo": "fa-brands fa-java",
      "certificate": {
        "certificateId": "CERT-001",
        "certificateName": "Python Programming",
        "issuedDate": "2023-01-15",
        "expirationDate": "2026-01-15",
        "file": "java-Prog.pdf"
      },
      "experience": [
        {
          "date": "2018 - 2019",
          "title": "Illustrator",
          "company": {
            "name": "Creative Mind",
            "url": "#"
          },
          "description": "Created original illustrations for digital and print media."
        },
        {
          "date": "2019 - 2021",
          "title": "UI/UX Designer",
          "company": {
            "name": "Pixel Perfect",
            "url": "#"
          },
          "description": "Designed user-friendly interfaces and enhanced user experience."
        }
      ],
      "education": [
        {
          "degree": "Bachelor's in Computer Science",
          "university": "XYZ University",
          "year": "2015 - 2019"
        },
        {
          "degree": "Master's in Software Engineering",
          "university": "ABC Institute",
          "year": "2020 - 2022"
        }
      ]
    }
  ]
}
